MANIFEST.in
README.rst
setup.cfg
setup.py
json_logic/__init__.py
mp_json_logic.egg-info/PKG-INFO
mp_json_logic.egg-info/SOURCES.txt
mp_json_logic.egg-info/dependency_links.txt
mp_json_logic.egg-info/requires.txt
mp_json_logic.egg-info/top_level.txt