Metadata-Version: 2.1
Name: mp-json-logic
Version: 0.7.0a0
Summary: Build complex rules, serialize them as JSON, and execute them in Python
Home-page: https://github.com/mptnt1988/json-logic-py
Author: mptnt1988
Author-email: mptnt1988@gmail.com
License: MIT
Keywords: json-logic
Platform: UNKNOWN
Classifier: Development Status :: 4 - Beta
Classifier: Intended Audience :: Developers
Classifier: Topic :: Software Development :: Libraries :: Python Modules
Classifier: License :: OSI Approved :: MIT License
Classifier: Programming Language :: Python :: 2
Classifier: Programming Language :: Python :: 2.6
Classifier: Programming Language :: Python :: 2.7
Classifier: Programming Language :: Python :: 3
Classifier: Programming Language :: Python :: 3.2
Classifier: Programming Language :: Python :: 3.3
Classifier: Programming Language :: Python :: 3.4
Provides-Extra: dev
Provides-Extra: test
